pyrs/__init__.py
pyrs/__main__.py
pyrs/analysis.py
pyrs/annotation_transformer.py
pyrs/cli.py
pyrs/clike.py
pyrs/context.py
pyrs/declaration_extractor.py
pyrs/mutability_transformer.py
pyrs/scope.py
pyrs/tracer.py
pyrs/transpiler.py
pyrs/tests/__init__.py
pyrs/tests/test_analysis.py
pyrs/tests/test_clike.py
pyrs/tests/test_context.py
pyrs/tests/test_scope.py
pyrs/tests/test_tracer.py
pyrs/tests/test_transpiler.py
python_rs-0.1.0.dist-info/LICENSE
python_rs-0.1.0.dist-info/METADATA
python_rs-0.1.0.dist-info/WHEEL
python_rs-0.1.0.dist-info/entry_points.txt
python_rs-0.1.0.dist-info/top_level.txt
python_rs-0.1.0.dist-info/RECORD
