Metadata-Version: 2.1
Name: python-rs
Version: 0.1.0
Summary: Python to Rust transpiler.
Home-page: http://github.com/konchunas/pyrs
Author: Julian Konchunas
Author-email: konchunas@gmail.com
License: MIT
Platform: UNKNOWN
Classifier: License :: OSI Approved :: MIT License
Classifier: Operating System :: OS Independent
Classifier: Programming Language :: Python :: 3
Classifier: Topic :: Software Development
Classifier: Topic :: Utilities
Requires-Python: >=3.0.0
